{
    "key": "group_556e40c01f051",
    "title": "Homepage",
    "fields": [
        {
            "key": "field_55ed0a49a5ff4",
            "label": "Featured Quote",
            "name": "featured_quote",
            "type": "wysiwyg",
            "instructions": "",
            "required": 0,
            "conditional_logic": 0,
            "wrapper": {
                "width": "",
                "class": "",
                "id": ""
            },
            "default_value": "",
            "tabs": "all",
            "toolbar": "full",
            "media_upload": 1
        },
        {
            "key": "field_557678ec2d6ba",
            "label": "Groups call to action",
            "name": "groups_call_to_action",
            "type": "wysiwyg",
            "instructions": "",
            "required": 0,
            "conditional_logic": 0,
            "wrapper": {
                "width": "",
                "class": "",
                "id": ""
            },
            "default_value": "",
            "tabs": "all",
            "toolbar": "full",
            "media_upload": 1
        }
    ],
    "location": [
        [
            {
                "param": "page",
                "operator": "==",
                "value": "20"
            }
        ]
    ],
    "menu_order": 0,
    "position": "normal",
    "style": "default",
    "label_placement": "top",
    "instruction_placement": "label",
    "hide_on_screen": "",
    "active": 1,
    "description": "",
    "modified": 1441598038
}